setup.py
pylint_celery/__init__.py
pylint_celery.egg-info/PKG-INFO
pylint_celery.egg-info/SOURCES.txt
pylint_celery.egg-info/dependency_links.txt
pylint_celery.egg-info/requires.txt
pylint_celery.egg-info/top_level.txt
test/test_func.py